galaxy/service/__init__.py
galaxy/service/constant.py
galaxy/service/env.py
galaxy/service/log.py
galaxy/service/pref.py
galaxy/service/service.py
galaxy_py_service-0.0.2.dist-info/AUTHORS
galaxy_py_service-0.0.2.dist-info/COPYING.md
galaxy_py_service-0.0.2.dist-info/LICENSE.txt
galaxy_py_service-0.0.2.dist-info/METADATA
galaxy_py_service-0.0.2.dist-info/WHEEL
galaxy_py_service-0.0.2.dist-info/RECORD
