Metadata-Version: 2.3
Name: galaxy-py-service
Version: 0.0.2
Summary: Python Service for the Galaxy Project
License: Apache-2.0
Keywords: galaxy,galaxy-service
Author: Bastien Saltel
Author-email: bastien.saltel@gmail.com
Maintainer: Bastien Saltel
Maintainer-email: bastien.saltel@gmail.com
Requires-Python: >=3.10
Classifier: Development Status :: 3 - Alpha
Classifier: Programming Language :: Python :: 3
Classifier: Operating System :: OS Independent
Requires-Dist: galaxy-py-utils
Requires-Dist: transitions
Project-URL: Changelog, https://github.com/bsaltel/galaxy-py-service/blob/main/CHANGELOG.md
Project-URL: Documentation, https://github.com/bsaltel/galaxy-py-service
Project-URL: Homepage, https://github.com/bsaltel/galaxy-py-service
Project-URL: Issues, https://github.com/bsaltel/galaxy-py-service/issues
Project-URL: Repository, https://github.com/bsaltel/galaxy-py-service.git
